{"UAc7kepzJPkrSn4uqTRvmw==":"background4.jpg","p5XEMafdDvvrEmXnti1Iog==":"img_20190518-213206-2698x3597.jpg","k/7iFQh98T2wu5dzob+cpg==":"future-of-investment-banking-850x474.jpg","6Li8FNiiN2FHbidepFuBPg==":"img_20190518-213206-400x533.jpeg","tApch1tsE5KyXlDs4890vQ==":"img_20190518-213206-240x320.jpg","MWEjfSXdB6rFJoSt6D1d1g==":"rukundo-240x214.jpg","cvtD08oStgbT0SZ5dN9TCQ==":"rukundo-240x214.jpeg","uyJRQjZ0E1rmycr7y9uzlQ==":"cola1-240x221.jpg","kbFCvGPgPoRZI855wlXFiQ==":"cola2-240x221.jpg","s2jaM8tu0pER1WupwCjCoQ==":"cola3-240x221.jpg"}